odoo8_addon_web_hideleftmenu-8.0.1.0.0.99.dev20-py2.7-nspkg.pth
odoo8_addon_web_hideleftmenu-8.0.1.0.0.99.dev20.dist-info/DESCRIPTION.rst
odoo8_addon_web_hideleftmenu-8.0.1.0.0.99.dev20.dist-info/METADATA
odoo8_addon_web_hideleftmenu-8.0.1.0.0.99.dev20.dist-info/RECORD
odoo8_addon_web_hideleftmenu-8.0.1.0.0.99.dev20.dist-info/WHEEL
odoo8_addon_web_hideleftmenu-8.0.1.0.0.99.dev20.dist-info/metadata.json
odoo8_addon_web_hideleftmenu-8.0.1.0.0.99.dev20.dist-info/namespace_packages.txt
odoo8_addon_web_hideleftmenu-8.0.1.0.0.99.dev20.dist-info/top_level.txt
odoo_addons/web_hideleftmenu/README.rst
odoo_addons/web_hideleftmenu/__init__.py
odoo_addons/web_hideleftmenu/__openerp__.py
odoo_addons/web_hideleftmenu/web_hideleftmenu_js.xml
odoo_addons/web_hideleftmenu/i18n/es.po
odoo_addons/web_hideleftmenu/i18n/fi.po
odoo_addons/web_hideleftmenu/i18n/fr.po
odoo_addons/web_hideleftmenu/i18n/it.po
odoo_addons/web_hideleftmenu/i18n/pt_BR.po
odoo_addons/web_hideleftmenu/i18n/pt_PT.po
odoo_addons/web_hideleftmenu/i18n/sl.po
odoo_addons/web_hideleftmenu/i18n/tr.po
odoo_addons/web_hideleftmenu/i18n/web_hideleftmenu.pot
odoo_addons/web_hideleftmenu/static/description/1.png
odoo_addons/web_hideleftmenu/static/description/2.png
odoo_addons/web_hideleftmenu/static/description/icon.png
odoo_addons/web_hideleftmenu/static/src/css/lib.css
odoo_addons/web_hideleftmenu/static/src/js/lib.js
odoo_addons/web_hideleftmenu/static/src/xml/lib.xml
